paginate/__init__.py
paginate/plugin.py
mkdocs_paginate_plugin-0.0.6.dist-info/METADATA
mkdocs_paginate_plugin-0.0.6.dist-info/WHEEL
mkdocs_paginate_plugin-0.0.6.dist-info/entry_points.txt
mkdocs_paginate_plugin-0.0.6.dist-info/top_level.txt
mkdocs_paginate_plugin-0.0.6.dist-info/RECORD
