Metadata-Version: 2.1
Name: mkdocs-paginate-plugin
Version: 0.0.6
Summary: Mkdocs paginate plugin
Home-page: https://github.com/kubilus1/mkdocs-paginate-plugin
Author: Matt Kubilus
License: UNKNOWN
Platform: UNKNOWN
Requires-Dist: mkdocs (>=0.17)
